{
  "firstNode" : {
    "nextNode" : {
      "nextNode" : {
        "nextNode" : {
          "user" : {
            "name" : "noel",
            "email" : "www",
            "password" : "8054da645a387dbfb06654d69f0d0201",
            "address" : "www",
            "phoneNumber" : 2345,
            "rol" : 1,
            "id" : 666
          }
        },
        "user" : {
          "name" : "noel",
          "email" : "de",
          "password" : "7fa3b767c460b54a2be4d49030b349c7",
          "address" : "sss",
          "phoneNumber" : 234,
          "rol" : 3,
          "id" : 144
        }
      },
      "user" : {
        "name" : "daniel",
        "email" : "dfds",
        "password" : "03c7c0ace395d80182db07ae2c30f034",
        "address" : "2",
        "phoneNumber" : 234,
        "rol" : 3,
        "id" : 1111
      }
    },
    "user" : {
      "name" : "daniel",
      "email" : "sss",
      "password" : "8054da645a387dbfb06654d69f0d0201",
      "address" : "sss",
      "phoneNumber" : 2345,
      "rol" : 3,
      "id" : 1234
    }
  },
  "node" : {
    "user" : {
      "name" : "noel",
      "email" : "www",
      "password" : "8054da645a387dbfb06654d69f0d0201",
      "address" : "www",
      "phoneNumber" : 2345,
      "rol" : 3,
      "id" : 666
    }
  }
}